milvus_connector/__init__.py
milvus_connector/_interceptor.py
milvus_connector/core/__init__.py
milvus_connector/core/_const.py
milvus_connector/core/_param.py
milvus_connector/core/_types.py
milvus_connector/core/milvus.py
milvus_connector/core/query_node.py
milvus_connector/core/util.py
milvus_connector/protocol/__init__.py
milvus_connector/protocol/common_pb2.py
milvus_connector/protocol/common_pb2.pyi
milvus_connector/protocol/common_pb2_grpc.py
milvus_connector/protocol/data_coord_pb2.py
milvus_connector/protocol/data_coord_pb2.pyi
milvus_connector/protocol/data_coord_pb2_grpc.py
milvus_connector/protocol/etcd_meta_pb2.py
milvus_connector/protocol/etcd_meta_pb2.pyi
milvus_connector/protocol/etcd_meta_pb2_grpc.py
milvus_connector/protocol/feder_pb2.py
milvus_connector/protocol/feder_pb2.pyi
milvus_connector/protocol/feder_pb2_grpc.py
milvus_connector/protocol/index_cgo_msg_pb2.py
milvus_connector/protocol/index_cgo_msg_pb2.pyi
milvus_connector/protocol/index_cgo_msg_pb2_grpc.py
milvus_connector/protocol/index_coord_pb2.py
milvus_connector/protocol/index_coord_pb2.pyi
milvus_connector/protocol/index_coord_pb2_grpc.py
milvus_connector/protocol/internal_pb2.py
milvus_connector/protocol/internal_pb2.pyi
milvus_connector/protocol/internal_pb2_grpc.py
milvus_connector/protocol/milvus_pb2.py
milvus_connector/protocol/milvus_pb2.pyi
milvus_connector/protocol/milvus_pb2_grpc.py
milvus_connector/protocol/msg_pb2.py
milvus_connector/protocol/msg_pb2.pyi
milvus_connector/protocol/msg_pb2_grpc.py
milvus_connector/protocol/plan_pb2.py
milvus_connector/protocol/plan_pb2.pyi
milvus_connector/protocol/plan_pb2_grpc.py
milvus_connector/protocol/proxy_pb2.py
milvus_connector/protocol/proxy_pb2.pyi
milvus_connector/protocol/proxy_pb2_grpc.py
milvus_connector/protocol/query_coord_pb2.py
milvus_connector/protocol/query_coord_pb2.pyi
milvus_connector/protocol/query_coord_pb2_grpc.py
milvus_connector/protocol/rg_pb2.py
milvus_connector/protocol/rg_pb2.pyi
milvus_connector-0.1.0.dist-info/LICENSE
milvus_connector-0.1.0.dist-info/METADATA
milvus_connector-0.1.0.dist-info/WHEEL
milvus_connector-0.1.0.dist-info/RECORD
