Metadata-Version: 2.1
Name: milvus-connector
Version: 0.1.0
Summary: 
Author: SimFG
Author-email: simf00544@gmail.com
Requires-Python: >=3.8,<4.0
Classifier: Programming Language :: Python :: 3
Classifier: Programming Language :: Python :: 3.8
Classifier: Programming Language :: Python :: 3.9
Classifier: Programming Language :: Python :: 3.10
Classifier: Programming Language :: Python :: 3.11
Classifier: Programming Language :: Python :: 3.12
Requires-Dist: furl (>=2.1.3,<3.0.0)
Requires-Dist: grpcio (>=1.62.0,<2.0.0)
Requires-Dist: grpcio-tools (>=1.62.0,<2.0.0)
Requires-Dist: pydantic (>=2.6.3,<3.0.0)
Requires-Dist: typing-extensions (>=4.10.0,<5.0.0)
